rustalib-0.3.4.dist-info/METADATA
rustalib-0.3.4.dist-info/WHEEL
rustalib-0.3.4.dist-info/licenses/LICENSE
rustalib.libs/libgcc_s-e52197c3.so.1
rustalib/__init__.py
rustalib/atr.py
rustalib/ema.py
rustalib/macd.py
rustalib/rustalib.cpython-313-aarch64-linux-musl.so
rustalib/sma.py
rustalib-0.3.4.dist-info/RECORD
