Metadata-Version: 2.4
Name: rustalib
Version: 0.3.4
Classifier: Programming Language :: Rust
Classifier: Programming Language :: Python :: 3
Classifier: Programming Language :: Python :: Implementation :: CPython
Classifier: Programming Language :: Python :: Implementation :: PyPy
Classifier: License :: OSI Approved :: MIT License
Classifier: Operating System :: OS Independent
License-File: LICENSE
Summary: Python wrapper for rustalib-core, a high-performance technical analysis library written in Rust.
Home-Page: https://github.com/cuantilab
Author: Cuantilab
License: MIT
Requires-Python: >=3.8
Project-URL: Homepage, https://github.com/cuantilab/rustalib
Project-URL: Issues, https://github.com/cuantilab/rustalib/issues
Project-URL: Documentation, https://github.com/cuantilab/rustalib#readme
Project-URL: Changelog, https://github.com/cuantilab/rustalib/blob/main/CHANGELOG.md
